zipschema/__init__.py
zipschema/zipschema.py
zipschema-1.0.12.dist-info/LICENSE
zipschema-1.0.12.dist-info/METADATA
zipschema-1.0.12.dist-info/WHEEL
zipschema-1.0.12.dist-info/entry_points.txt
zipschema-1.0.12.dist-info/top_level.txt
zipschema-1.0.12.dist-info/RECORD
