Metadata-Version: 2.1
Name: zipschema
Version: 1.0.12
Summary: CLI tool for validating zipschema files and generating documentation.
Home-page: https://github.com/mrmessagewriter/zipschema
Author: Sean Hummel
License: UNKNOWN
Platform: UNKNOWN
Classifier: Programming Language :: Python :: 3
Classifier: License :: OSI Approved :: MIT License
Classifier: Operating System :: OS Independent
Requires-Python: >=3.6
License-File: LICENSE
Requires-Dist: pyyaml
Requires-Dist: jsonschema
Requires-Dist: jinja2
Requires-Dist: python-docx
